asynchrony/__init__.py
asynchrony/_constants.py
asynchrony/_helpers.py
asynchrony/_task.py
asynchrony/_tasks.py
asynchrony/py.typed
asynchrony-0.2.0.dist-info/LICENSE
asynchrony-0.2.0.dist-info/WHEEL
asynchrony-0.2.0.dist-info/METADATA
asynchrony-0.2.0.dist-info/RECORD
